cbrecommender/__init__.py
cbrecommender/cbrecommender.py
cbrecommender/helpers.py
cbrecommender-1.1.1.dist-info/LICENSE.txt
cbrecommender-1.1.1.dist-info/METADATA
cbrecommender-1.1.1.dist-info/WHEEL
cbrecommender-1.1.1.dist-info/top_level.txt
cbrecommender-1.1.1.dist-info/RECORD
