Metadata-Version: 2.1
Name: cbrecommender
Version: 1.1.1
Summary: A library for implementing Content-Based Recommendation Engines with ease!
Author-email: Akash S Panickar <akashsabu@ymail.com>
Project-URL: Homepage, https://github.com/mochatek/cbrecommender
Keywords: content-based-recommender,recommendation-engine
Classifier: License :: OSI Approved :: MIT License
Classifier: Programming Language :: Python :: 3
Classifier: Operating System :: OS Independent
Requires-Python: >=3.7
License-File: LICENSE.txt
Requires-Dist: pandas
